ip_fetcher/__init__.py
ip_fetcher/cli.py
ip_fetcher/ip_utils.py
ip_fetcher-0.3.4.2.dist-info/METADATA
ip_fetcher-0.3.4.2.dist-info/WHEEL
ip_fetcher-0.3.4.2.dist-info/entry_points.txt
ip_fetcher-0.3.4.2.dist-info/license.txt
ip_fetcher-0.3.4.2.dist-info/top_level.txt
ip_fetcher-0.3.4.2.dist-info/RECORD
