Metadata-Version: 2.1
Name: ip-fetcher
Version: 0.3.4.2
Summary: A Python library to fetch public and private IP addresses.
Home-page: UNKNOWN
License: MIT
Keywords: IP address,public IP,private IP,network utilities,Python library,CLI tool,IP fetching,IP
Platform: UNKNOWN
Classifier: License :: OSI Approved :: MIT License
Classifier: Programming Language :: Python :: 3.6
Classifier: Programming Language :: Python :: 3.7
Classifier: Programming Language :: Python :: 3.8
Classifier: Programming Language :: Python :: 3.9
Classifier: Programming Language :: Python :: 3.10
Classifier: Operating System :: Microsoft :: Windows
Requires-Python: >=3.6
License-File: license.txt
Requires-Dist: requests>=2.20.0
Requires-Dist: setuptools
Requires-Dist: ipaddress
Requires-Dist: beautifulsoup4
